README.rst
setup.py
mq_http_sdk/__init__.py
mq_http_sdk/mq_client.py
mq_http_sdk/mq_consumer.py
mq_http_sdk/mq_exception.py
mq_http_sdk/mq_http.py
mq_http_sdk/mq_producer.py
mq_http_sdk/mq_request.py
mq_http_sdk/mq_tool.py
mq_http_sdk/mq_xml_handler.py
mq_http_sdk/pkg_info.py
mq_http_sdk.egg-info/PKG-INFO
mq_http_sdk.egg-info/SOURCES.txt
mq_http_sdk.egg-info/dependency_links.txt
mq_http_sdk.egg-info/top_level.txt