Metadata-Version: 1.0
Name: mq-http-sdk
Version: 1.0.1
Summary: Aliyun Message Queue(MQ) Http Python SDK
Home-page: https://github.com/aliyunmq/mq-http-python-sdk
Author: aliyunmq
Author-email: UNKNOWN
License: MIT
Platform: UNKNOWN
